README.rst
setup.py
casslr/__init__.py
casslr/app.py
casslr/szradm.py
casslr/version.py
casslr.egg-info/PKG-INFO
casslr.egg-info/SOURCES.txt
casslr.egg-info/dependency_links.txt
casslr.egg-info/requires.txt
casslr.egg-info/top_level.txt
casslr/test/__init__.py
casslr/test/test_casslr.py
casslr/test/test_szradm.py
casslr/test/util.py